{
  "property_id": "UDR-001",
  "listing_scope": "single_property",
  "property_type": "hotel",
  "display_name": "Hotel Lakeview Residency",
  "star_rating": 3,
  "location_type": "lakeside",
  "description": "A 30-room 3-star hotel overlooking Fateh Sagar Lake in Udaipur.",
  "currency": "INR",
  "opening_date": "2018-10-01",
  "is_currently_open": true,
  "address": {
    "line1": "47 Rani Road", "line2": "Near Fateh Sagar Lake",
    "city": "Udaipur", "state": "Rajasthan", "country": "IN", "postal_code": "313001",
    "latitude": 24.5894, "longitude": 73.6790
  },
  "contact": { "full_name": "Rohit Mehta", "email": "manager@lakeviewresidency-test.example", "phone": "+919829012345" },
  "compliance": { "legal_entity_name": "Lakeview Hospitality Pvt Ltd", "business_type": "business", "gstin": "08AABCL1234M1Z6", "pan": "AABCL1234M" },
  "room_types": [
    { "name": "Standard Double", "count": 12, "max_adults": 2, "max_children": 1, "beds": [{ "bed_type": "double", "count": 1 }], "bathroom": "private", "size_sqm": 20.0, "base_rate": 2400, "currency": "INR", "room_amenities": ["ac", "tv", "wifi"] },
    { "name": "Deluxe Lake-View", "count": 12, "max_adults": 2, "max_children": 2, "beds": [{ "bed_type": "queen", "count": 1 }], "bathroom": "private", "size_sqm": 26.0, "base_rate": 3800, "currency": "INR", "extra_bed_available": true, "room_amenities": ["ac", "tv", "wifi", "minibar", "balcony"] },
    { "name": "Family Suite", "count": 6, "max_adults": 4, "max_children": 2, "beds": [{ "bed_type": "king", "count": 1 }, { "bed_type": "single", "count": 2 }], "bathroom": "private", "size_sqm": 42.0, "base_rate": 6200, "currency": "INR", "extra_bed_available": true, "room_amenities": ["ac", "tv", "wifi", "minibar", "balcony", "bathtub"] }
  ],
  "facilities": {
    "parking": { "available": true, "type": "free", "on_site": true },
    "breakfast": { "available": true, "type": "buffet", "price_per_person": 350, "currency": "INR" },
    "internet": { "wifi": true, "free": true, "coverage": "all_areas" },
    "swimming_pool": true, "fitness_center": true, "restaurant": true, "bar": true,
    "room_service": true, "airport_shuttle": true, "laundry": true, "elevator": true, "family_rooms": true,
    "languages_spoken": ["English", "Hindi", "Rajasthani"]
  },
  "photos": [
    { "path": "examples/photos/facade.jpg", "caption": "Facade" },
    { "path": "examples/photos/pool.jpg", "caption": "Pool" }
  ],
  "policy": {
    "checkin_from": "14:00", "checkout_until": "11:00",
    "cancellation_tier": "moderate", "free_cancellation_until_hours": 24, "prepayment": "partial",
    "min_checkin_age": 18, "smoking_allowed": false, "pets_allowed": false,
    "payment_methods": ["cash", "visa", "mastercard", "amex", "upi"],
    "child_policy": { "children_allowed": true, "free_stay_under_age": 6, "extra_bed_fee": 800, "crib_available": true, "crib_fee": 0 }
  }
}
